itclib/__init__.py
itclib/database/ITCInfluxdb.py
itclib/database/__init__.py
itclib/database/exceptions.py
itclib-0.1.1.dist-info/METADATA
itclib-0.1.1.dist-info/WHEEL
itclib-0.1.1.dist-info/RECORD
