Metadata-Version: 2.1
Name: itclib
Version: 0.1.1
Summary: Conjunto de herramientas para realizar operaciones variadas
Author: CristianTacoronteRivero
Author-email: tacoronteriverocristian@gmail.com
Requires-Python: >=3.10,<4.0
Classifier: Programming Language :: Python :: 3
Classifier: Programming Language :: Python :: 3.10
Classifier: Programming Language :: Python :: 3.11
Requires-Dist: influxdb (>=5.3.1,<6.0.0)
Requires-Dist: numpy (>=1.26.4,<2.0.0)
Requires-Dist: pandas (>=2.2.1,<3.0.0)
